pyproject.toml
setup.py
nimsameed/__init__.py
nimsameed/nimsameed.py
nimsameed.egg-info/PKG-INFO
nimsameed.egg-info/SOURCES.txt
nimsameed.egg-info/dependency_links.txt
nimsameed.egg-info/not-zip-safe
nimsameed.egg-info/top_level.txt