Metadata-Version: 2.1
Name: nimsameed
Version: 0.2
Summary: The game built on Reinforcement Q-learning. The agent in the game always try to win.
Author: Saad and Sameed
